cas/__init__.py
cas/db.py
cas/database/database.json
cas_python-0.1.0.dist-info/METADATA
cas_python-0.1.0.dist-info/WHEEL
cas_python-0.1.0.dist-info/top_level.txt
cas_python-0.1.0.dist-info/RECORD
