Metadata-Version: 2.1
Name: cas-python
Version: 0.1.0
Summary: Database of CAS Registry Number for Python
Author: Antonio Silva
Maintainer: Antonio Silva
Project-URL: Homepage, https://github.com/asergios/cas-python
Project-URL: Bug Reports, https://github.com/asergios/cas-python/issues
Project-URL: Source, https://github.com/asergios/cas-python/
Keywords: cas,registry,chemical,abstracts,service,database,formula
Classifier: Development Status :: 4 - Beta
Classifier: Intended Audience :: Developers
Classifier: Intended Audience :: Science/Research
Classifier: Programming Language :: Python :: 3
Classifier: Operating System :: OS Independent
Requires-Python: >=3.6
Provides-Extra: dev
Requires-Dist: pre-commit<4.0.0,>=3.8.0; extra == "dev"
Requires-Dist: ruff<1.0.0,>=0.6.1; extra == "dev"
Requires-Dist: black<25.0.0,>=24.8.0; extra == "dev"
Requires-Dist: mypy<2.0.0,>=1.11.1; extra == "dev"
Provides-Extra: test
